weatheruz/__init__.py
weatheruz/main.py
weatheruz-0.7.dist-info/METADATA
weatheruz-0.7.dist-info/WHEEL
weatheruz-0.7.dist-info/top_level.txt
weatheruz-0.7.dist-info/RECORD
