Metadata-Version: 2.2
Name: weatheruz
Version: 0.7
Summary: 🇺🇿 O'zbekistondagi ob-havo ma'lumotlarini olish uchun qulay kutubxona! 🌤️
Home-page: https://taplink.cc/qaxxorovc
Author: Axmadjon Qaxxorov
Project-URL: 📌 Taplink, https://taplink.cc/qaxxorovc
Project-URL: 📺 YouTube, https://youtube.com/@axmadjonqaxxorovc
Project-URL: 💻 GitHub, https://github.com/axmadjonqaxxorovc
Keywords: weather,Uzbekistan,ob-havo,API,Python
Classifier: Programming Language :: Python :: 3
Classifier: License :: OSI Approved :: MIT License
Classifier: Operating System :: OS Independent
Requires-Python: >=3.6
Dynamic: author
Dynamic: classifier
Dynamic: description
Dynamic: description-content-type
Dynamic: home-page
Dynamic: keywords
Dynamic: project-url
Dynamic: requires-python
Dynamic: summary
